kalabash_dmarc/__init__.py
kalabash_dmarc/admin.py
kalabash_dmarc/apps.py
kalabash_dmarc/constants.py
kalabash_dmarc/forms.py
kalabash_dmarc/handlers.py
kalabash_dmarc/kalmonak_extension.py
kalabash_dmarc/lib.py
kalabash_dmarc/models.py
kalabash_dmarc/urls.py
kalabash_dmarc/views.py
kalabash_dmarc/locale/en/LC_MESSAGES/django.mo
kalabash_dmarc/locale/en/LC_MESSAGES/django.po
kalabash_dmarc/locale/fr/LC_MESSAGES/django.mo
kalabash_dmarc/locale/fr/LC_MESSAGES/django.po
kalabash_dmarc/management/__init__.py
kalabash_dmarc/management/commands/__init__.py
kalabash_dmarc/management/commands/import_aggregated_report.py
kalabash_dmarc/migrations/0001_initial.py
kalabash_dmarc/migrations/0002_auto_20180124_2311.py
kalabash_dmarc/migrations/0003_auto_20200227_0936.py
kalabash_dmarc/migrations/__init__.py
kalabash_dmarc/templates/kalabash_dmarc/_result_detail.html
kalabash_dmarc/templates/kalabash_dmarc/domain_report.html
kalabash_dmarc/templatetags/__init__.py
kalabash_dmarc/templatetags/dmarc_tags.py
kalabash_dmarc/tests/__init__.py
kalabash_dmarc/tests/mixins.py
kalabash_dmarc/tests/test_management_command.py
kalabash_dmarc/tests/test_views.py
kalabash_dmarc/tests/fail-reports/Report_Domain_ngyn.org_Submitter_163.com_Report-ID_aggr_report_ngyn.org_20150705_163-failed.com.eml
kalabash_dmarc/tests/reports/Report_Domain_ngyn.org_Submitter_163.com_Report-ID_aggr_report_ngyn.org_20150705_163.com.eml
kalabash_dmarc/tests/reports/Report_Domain_ngyn.org_Submitter_amazon.com_Report-ID_aggr_report_ngyn.org_20210607-ignored.eml
kalabash_dmarc/tests/reports/Report_Domain_ngyn.org_Submitter_amazon.com_Report-ID_aggr_report_ngyn.org_20210622.eml
kalabash_dmarc/tests/reports/Report_Domain_ngyn.org_Submitter_fastmail.com_Report-ID_2015.06.23.5672770.eml
kalabash_dmarc/tests/reports/Report_Domain_ngyn.org_Submitter_google.com_Report-ID_1282989064754998675.eml
kalabash_dmarc/tests/reports/Report_Domain_ngyn.org_Submitter_google.com_Report-ID_14872432101891615947.eml
kalabash_dmarc-1.2.10.dist-info/LICENSE
kalabash_dmarc-1.2.10.dist-info/METADATA
kalabash_dmarc-1.2.10.dist-info/WHEEL
kalabash_dmarc-1.2.10.dist-info/top_level.txt
kalabash_dmarc-1.2.10.dist-info/RECORD
