Metadata-Version: 2.1
Name: kalabash-dmarc
Version: 1.2.10
Summary: DMARC related tools for Kalabash
Home-page: https://alphamonak.com/
Author: Alphamonak Solutions
Author-email: amonak@alphamonak.com
License: MIT
Keywords: email dmarc
Platform: UNKNOWN
Classifier: Development Status :: 4 - Beta
Classifier: Environment :: Web Environment
Classifier: Framework :: Django :: 2.2
Classifier: Intended Audience :: System Administrators
Classifier: License :: OSI Approved :: MIT License
Classifier: Operating System :: OS Independent
Classifier: Programming Language :: Python :: 3
Classifier: Programming Language :: Python :: 3.6
Classifier: Programming Language :: Python :: 3.7
Classifier: Programming Language :: Python :: 3.8
Classifier: Topic :: Communications :: Email
Classifier: Topic :: Internet :: WWW/HTTP
License-File: LICENSE
Requires-Dist: kalabash (>=2.0.0)
Requires-Dist: tldextract (>=2.0.2)
Requires-Dist: defusedxml (>=0.6.0)
Requires-Dist: python-magic (>=0.4.24)
